neopixel_plus/__init__.py
neopixel_plus/neopixel_plus.py
neopixel_plus/animations/__init__.py
neopixel_plus/animations/beats_up_and_down.py
neopixel_plus/animations/light_up.py
neopixel_plus/animations/moving_dot.py
neopixel_plus/animations/rainbow.py
neopixel_plus/animations/transition.py
neopixel_plus/helper/__init__.py
neopixel_plus/helper/colors.py
neopixel_plus-1.7.dist-info/LICENSE
neopixel_plus-1.7.dist-info/METADATA
neopixel_plus-1.7.dist-info/WHEEL
neopixel_plus-1.7.dist-info/top_level.txt
neopixel_plus-1.7.dist-info/RECORD
