Metadata-Version: 2.1
Name: neopixel-plus
Version: 1.7
Summary: The NeoPixel library plus animations and terminal testing mode - so you can see how your LEDs would behave directly in the terminal, without any microcontroller.
Home-page: https://github.com/glowingkitty/NeoPixelPlus
Author: Marco
License: UNKNOWN
Platform: UNKNOWN
Classifier: Programming Language :: Python :: 3
Classifier: License :: OSI Approved :: MIT License
Classifier: Operating System :: OS Independent
Requires-Python: >=3.6
Requires-Dist: colr
Requires-Dist: rpi-ws281x
Requires-Dist: adafruit-circuitpython-neopixel
